timestream/__init__.py
timestream/_version.py
timestream/manipulate/__init__.py
timestream/manipulate/configuration.py
timestream/manipulate/correct_detect.py
timestream/manipulate/pipecomponents.py
timestream/manipulate/pipeline.py
timestream/manipulate/plantSegmenter.py
timestream/manipulate/pot.py
timestream/parse/__init__.py
timestream/parse/validate.py
timestream/util/__init__.py
timestream/util/imgmeta.py
timestream/util/layouts.py
timestream/util/validation.py
timestream-0.3.0.data/scripts/run_pipeline.py
timestream-0.3.0.data/scripts/timestream2netcdf.py
timestream-0.3.0.dist-info/DESCRIPTION.rst
timestream-0.3.0.dist-info/METADATA
timestream-0.3.0.dist-info/RECORD
timestream-0.3.0.dist-info/WHEEL
timestream-0.3.0.dist-info/metadata.json
timestream-0.3.0.dist-info/top_level.txt
