Metadata-Version: 2.0
Name: timestream
Version: 0.3.0
Summary: 
Requires-Dist: ExifRead (==1.4.2)
Requires-Dist: docopt (==0.6.2)
Requires-Dist: scikit-image (>=0.10.1)
Requires-Dist: voluptuous (==0.8.4)
